kratelabs/__init__.py
kratelabs/cli.py
kratelabs-0.2.1.dist-info/DESCRIPTION.rst
kratelabs-0.2.1.dist-info/METADATA
kratelabs-0.2.1.dist-info/RECORD
kratelabs-0.2.1.dist-info/WHEEL
kratelabs-0.2.1.dist-info/entry_points.txt
kratelabs-0.2.1.dist-info/metadata.json
kratelabs-0.2.1.dist-info/top_level.txt
