Metadata-Version: 2.0
Name: kratelabs
Version: 0.2.1
Summary: Kratelab's helpful scripts for MapboxGL maps.
Home-page: UNKNOWN
Author: UNKNOWN
Author-email: UNKNOWN
License: UNKNOWN
Platform: UNKNOWN
Requires-Dist: click
Requires-Dist: geocoder
Requires-Dist: requests
